[
  {
    "id": "106678",
    "title": "Jungle Erotic",
    "poster": "https://image.tmdb.org/t/p/w1280/rkMHlp42CDJUEB4GKsn3LC5znGC.jpg",
    "overview": "Young women have an adventure in the African jungle - where they are harassed by gentle men, and wild monkeys.",
    "release_date": 26265600,
    "genre": [
     "Adventure",
     "Drama"
    ]
   },
   {
    "id": "490410",
    "title": "48 Christmas Wishes",
    "poster": "https://image.tmdb.org/t/p/w1280/mrcA62O9j8y4gsSpftMKVcvrzCI.jpg",
    "overview": "Holiday magic has never gleamed brighter as Santa’s Elves head out on an adventure to bring every boy and girl their Christmas wish while also bringing a family back together in this heartfelt Christmas movie from Gaumont. After accidentally destroying a bag of Christmas wishes from a small town on the eve of Christmas Eve, two junior elves learn that if even one wish goes unfulfilled, Christmas could be extinguished forever. For the first time in their lives, the elves Mindy and Cam venture out of the North Pole and sneak into Minnedoza to collect the lost wishes. Along the way they enlist the help of young Blake, whose family has a difficult time celebrating Christmas since his father died. With their deadline fast approaching, Mindy and Cam have only one more wish to find…but whose could it be? It’s up to Mindy and Cam to find out and save Christmas!",
    "release_date": 1512086400,
    "genre": [
     "Family",
     "Adventure",
     "Comedy",
     "TV Movie"
    ]
   },
   {
    "id": "285841",
    "title": "Elephant Song",
    "poster": "https://image.tmdb.org/t/p/w1280/9pHl6RmMIDyPmQW1XUJ2Mahsr3M.jpg",
    "overview": "A psychiatrist is drawn into a complex mind game when he questions a disturbed patient about the disappearance of a colleague.",
    "release_date": 1409792400,
    "genre": []
   }
]
